<?xml version="1.0" encoding="UTF-8"?>
<!--
	Processing Task Installer.
	It is possible to uninstall tasks or install new tasks added to the plugin or scripts folder.
	The task installation order is very sensible, because some tasks depend on results of others.
-->
<tasks>
    <!--<task script="ExampleScriptTask.js"></task>-->
    <task class="dpf.sp.gpinf.indexer.process.task.SkipCommitedTask"></task>
    <task class="dpf.sp.gpinf.indexer.process.task.IgnoreHardLinkTask"></task>
    <task class="dpf.sp.gpinf.indexer.process.task.TempFileTask"></task>
    
    <task class="dpf.sp.gpinf.indexer.process.task.SignatureTask"></task>
    <task class="dpf.sp.gpinf.indexer.process.task.SetTypeTask"></task>
    <task class="dpf.sp.gpinf.indexer.process.task.SetCategoryTask"></task>
    <task script="RefineCategoryTask.js"></task>
    
    <!--tasks that ignore items should be after SetCategoryTask, so category of ignored items will be included in CSV properties file-->
    <task class="dpf.sp.gpinf.indexer.process.task.HashTask"></task>
    <task class="dpf.sp.gpinf.indexer.process.task.KFFTask"></task>
    <task class="dpf.sp.gpinf.indexer.process.task.LedKFFTask"></task>
    <task class="dpf.sp.gpinf.indexer.process.task.DuplicateTask"></task>
    
    <task class="dpf.sp.gpinf.indexer.process.task.transcript.AudioTranscriptTask"></task>
    <task class="dpf.sp.gpinf.indexer.process.task.VideoThumbTask"></task> <!--see issue #100-->
    <task class="dpf.sp.gpinf.indexer.process.task.ParsingTask"></task>
    <task class="dpf.sp.gpinf.indexer.process.task.regex.RegexTask"></task>
    <task class="dpf.sp.gpinf.indexer.process.task.LanguageDetectTask"></task>
    <task class="dpf.sp.gpinf.indexer.process.task.NamedEntityTask"></task>
    <task class="dpf.sp.gpinf.indexer.process.task.ExportFileTask"></task>
    <task class="dpf.sp.gpinf.indexer.process.task.MakePreviewTask"></task>
    
    <task class="dpf.sp.gpinf.indexer.process.task.ImageThumbTask"></task>
    <task class="dpf.sp.gpinf.indexer.process.task.DIETask"></task>
    <task class="dpf.sp.gpinf.indexer.process.task.ImageSimilarityTask"></task>
    <task class="dpf.sp.gpinf.indexer.process.task.PhotoDNATask"></task>
    <task class="dpf.sp.gpinf.indexer.process.task.PhotoDNALookup"></task>
    <!--<task script="NSFWNudityDetectTask.py"></task>-->
    
    <!--Carving must be installed before IndexTask because it sets hasChildren property in parent items-->
    <task class="dpf.sp.gpinf.indexer.process.task.KFFCarveTask"></task>
    <task class="dpf.sp.gpinf.carver.CarverTask"></task>
    <task class="dpf.sp.gpinf.indexer.process.task.KnownMetCarveTask"></task>
    
    <task class="dpf.sp.gpinf.indexer.process.task.FragmentLargeBinaryTask"></task>
    <task class="dpf.sp.gpinf.indexer.process.task.EntropyTask"></task>
    <task class="dpf.sp.gpinf.indexer.process.task.ElasticSearchIndexTask"></task>
    <task class="dpf.sp.gpinf.indexer.process.task.IndexTask"></task>
    
    <task class="dpf.sp.gpinf.indexer.process.task.ExportCSVTask"></task>
    <task class="dpf.sp.gpinf.indexer.process.task.HTMLReportTask"></task>
</tasks>